pandaserver/__init__.py
pandaserver/brokerage/ErrorCode.py
pandaserver/brokerage/SiteMapper.py
pandaserver/brokerage/__init__.py
pandaserver/brokerage/broker.py
pandaserver/config/__init__.py
pandaserver/config/config_utils.py
pandaserver/config/daemon_config.py
pandaserver/config/panda_config.py
pandaserver/configurator/Carbon.py
pandaserver/configurator/Configurator.py
pandaserver/configurator/__init__.py
pandaserver/configurator/aux.py
pandaserver/daemons/__init__.py
pandaserver/daemons/master.py
pandaserver/daemons/master_systemd.py
pandaserver/daemons/utils.py
pandaserver/daemons/scripts/__init__.py
pandaserver/daemons/scripts/add_main.py
pandaserver/daemons/scripts/add_sub.py
pandaserver/daemons/scripts/cache_pilots.py
pandaserver/daemons/scripts/cache_schedconfig.py
pandaserver/daemons/scripts/carbon.py
pandaserver/daemons/scripts/configurator.py
pandaserver/daemons/scripts/copyArchive.py
pandaserver/daemons/scripts/datasetManager.py
pandaserver/daemons/scripts/dummy_test.py
pandaserver/daemons/scripts/evpPD2P.py
pandaserver/daemons/scripts/metric_collector.py
pandaserver/daemons/scripts/panda_activeusers_query.py
pandaserver/daemons/scripts/pilotStreaming.py
pandaserver/daemons/scripts/process_workflow_files_daemon.py
pandaserver/daemons/scripts/recover_lost_files_daemon.py
pandaserver/daemons/scripts/task_evaluator.py
pandaserver/daemons/scripts/tmpwatch.py
pandaserver/daemons/scripts/worker_synchronization.py
pandaserver/dataservice/Activator.py
pandaserver/dataservice/AdderAtlasPlugin.py
pandaserver/dataservice/AdderDummyPlugin.py
pandaserver/dataservice/AdderGen.py
pandaserver/dataservice/AdderPluginBase.py
pandaserver/dataservice/AdderResult.py
pandaserver/dataservice/AdderSimplePlugin.py
pandaserver/dataservice/Closer.py
pandaserver/dataservice/CloserAtlasPlugin.py
pandaserver/dataservice/DDM.py
pandaserver/dataservice/DDMHandler.py
pandaserver/dataservice/DataService.py
pandaserver/dataservice/DataServiceUtils.py
panda_server-0.0.69.dist-info/LICENSE.txt
panda_server-0.0.69.dist-info/METADATA
panda_server-0.0.69.dist-info/WHEEL
panda_server-0.0.69.dist-info/top_level.txt
panda_server-0.0.69.dist-info/RECORD
