Metadata-Version: 2.1
Name: panda-server
Version: 0.0.69
Summary: PanDA Server Package
Home-page: https://twiki.cern.ch/twiki/bin/view/Atlas/PanDA
Author: Panda Team
Author-email: atlas-adc-panda@cern.ch
License: GPL
License-File: LICENSE.txt
Requires-Dist: panda-common >=0.0.43
Requires-Dist: panda-client-light >=1.5.55
Requires-Dist: pyOpenSSL
Requires-Dist: python-daemon
Requires-Dist: mod-wsgi
Requires-Dist: six
Requires-Dist: stomp.py
Requires-Dist: pyyaml
Requires-Dist: pyjwt
Requires-Dist: requests
Requires-Dist: psutil >=5.4.8
Requires-Dist: idds-common
Requires-Dist: idds-client
Requires-Dist: idds-workflow >=1.1.0
Requires-Dist: idds-doma
Requires-Dist: idds-atlas
Requires-Dist: ruamel.yaml
Requires-Dist: cwl-utils >=0.13
Requires-Dist: packaging
Requires-Dist: snakemake ==6.15.5
Requires-Dist: numpy
Requires-Dist: scipy
Provides-Extra: atlasprod
Requires-Dist: cx-Oracle ; extra == 'atlasprod'
Requires-Dist: rucio-clients ; extra == 'atlasprod'
Requires-Dist: elasticsearch ; extra == 'atlasprod'
Requires-Dist: numpy ; extra == 'atlasprod'
Requires-Dist: scipy ; extra == 'atlasprod'
Provides-Extra: elasticsearch
Requires-Dist: elasticsearch ; extra == 'elasticsearch'
Provides-Extra: mysql
Requires-Dist: mysqlclient ; extra == 'mysql'
Provides-Extra: oracle
Requires-Dist: cx-Oracle ; extra == 'oracle'
Provides-Extra: postgres
Requires-Dist: psycopg2-binary ; extra == 'postgres'
Provides-Extra: rucio
Requires-Dist: rucio-clients ; extra == 'rucio'
